flask_session_mysql/__init__.py
flask_session_mysql/fsm.py
flask_session_mysql-0.0.2.dist-info/METADATA
flask_session_mysql-0.0.2.dist-info/WHEEL
flask_session_mysql-0.0.2.dist-info/top_level.txt
flask_session_mysql-0.0.2.dist-info/RECORD
