Metadata-Version: 2.1
Name: flask-session-mysql
Version: 0.0.2
Summary: flask_session_mysql adds server side session manager making applications for flask more secure and efficient in MySQL
Home-page: https://github.com/Fabioblyk/flask-session-mysql
Author: Fabioblyk
Author-email: fabioblyk12@gmail.com
License: MIT
Classifier: Programming Language :: Python :: 3
Classifier: License :: OSI Approved :: MIT License
Classifier: Operating System :: OS Independent
Requires-Python: >=3.9
Requires-Dist: flask
Requires-Dist: mysql-connector-python
